parkinglot/__init__.py
parkinglot/config.py
parkinglot/db.py
parkinglot/ocr_validator.py
parkinglot/parkinglot_interface.py
parkinglot/utils.py
parkinglot-0.0.19.dist-info/METADATA
parkinglot-0.0.19.dist-info/WHEEL
parkinglot-0.0.19.dist-info/top_level.txt
parkinglot-0.0.19.dist-info/RECORD
